rmtree.py
setup.py
rmtree.egg-info/PKG-INFO
rmtree.egg-info/SOURCES.txt
rmtree.egg-info/dependency_links.txt
rmtree.egg-info/entry_points.txt
rmtree.egg-info/top_level.txt