Metadata-Version: 1.0
Name: rmtree
Version: 1.0
Summary: A sweet and simple python wrapper to shutil.rmtree
Home-page: UNKNOWN
Author: Jose Luis Naranjo Gomez
Author-email: luisnaranjo733@hotmail.com
License: UNKNOWN
Platform: UNKNOWN
